dg_query_analysis/__init__.py
dg_query_analysis/processor_base.py
dg_query_analysis/const/__init__.py
dg_query_analysis/const/hanlp_dep.py
dg_query_analysis/const/jiaba_posseg.py
dg_query_analysis/processor_callback_str/__init__.py
dg_query_analysis/processor_callback_str/processor_callback_str.py
dg_query_analysis/processor_core_word/__init__.py
dg_query_analysis/processor_core_word/processor_core_word.py
dg_query_analysis/processor_cut_phrase/__init__.py
dg_query_analysis/processor_cut_phrase/processor_cut_phrase.py
dg_query_analysis/processor_cut_words/__init__.py
dg_query_analysis/processor_cut_words/processor_cut_words.py
dg_query_analysis/processor_extract_info/__init__.py
dg_query_analysis/processor_extract_info/processor_extract_info.py
dg_query_analysis/processor_hanlp_dep/__init__.py
dg_query_analysis/processor_hanlp_dep/processor_hanlp_dep.py
dg_query_analysis/processor_keyword/__init__.py
dg_query_analysis/processor_keyword/processor_keyword.py
dg_query_analysis/processor_name/__init__.py
dg_query_analysis/processor_name/processor_name.py
dg_query_analysis/processor_normal_noun/__init__.py
dg_query_analysis/processor_normal_noun/processor_normal_noun.py
dg_query_analysis/processor_person_intention/__init__.py
dg_query_analysis/processor_person_intention/processor_person_intention.py
dg_query_analysis/processor_scope_words/__init__.py
dg_query_analysis/processor_scope_words/processor_scope_words.py
dg_query_analysis/processor_simple_zh/__init__.py
dg_query_analysis/processor_simple_zh/processor_simple_zh.py
dg_query_analysis/processor_stock_recog/__init__.py
dg_query_analysis/processor_stock_recog/processor_stock_recog.py
dg_query_analysis/processor_stopwords/__init__.py
dg_query_analysis/processor_stopwords/processor_stopwords.py
dg_query_analysis/processor_synonyms/__init__.py
dg_query_analysis/processor_synonyms/processor_synonyms.py
dg_query_analysis/utils/__init__.py
dg_query_analysis/utils/driver.py
dg_query_analysis/utils/error.py
dg_query_analysis-1.17.0.dist-info/METADATA
dg_query_analysis-1.17.0.dist-info/WHEEL
dg_query_analysis-1.17.0.dist-info/top_level.txt
dg_query_analysis-1.17.0.dist-info/RECORD
